CHANGES.txt
README.txt
setup.py
collective/__init__.py
collective.checkdocs.egg-info/PKG-INFO
collective.checkdocs.egg-info/SOURCES.txt
collective.checkdocs.egg-info/dependency_links.txt
collective.checkdocs.egg-info/entry_points.txt
collective.checkdocs.egg-info/namespace_packages.txt
collective.checkdocs.egg-info/not-zip-safe
collective.checkdocs.egg-info/requires.txt
collective.checkdocs.egg-info/top_level.txt
collective/checkdocs/__init__.py