Metadata-Version: 1.0
Name: collective.checkdocs
Version: 0.1.2
Summary: Distutils command to view and validate restructured text in package's long_description
Home-page: http://pypi.python.org/pypi/collective.checkdocs
Author: mFabrik Research Oy
Author-email: info@mfabrik.com
License: GPL
Keywords: rest distutils egg validator check validation restructured text html documentation
Platform: UNKNOWN
Classifier: Programming Language :: Python
Classifier: Topic :: Software Development :: Libraries :: Python Modules
